LICENSE
MANIFEST.in
README.rst
setup.py
twython_django.egg-info/PKG-INFO
twython_django.egg-info/SOURCES.txt
twython_django.egg-info/dependency_links.txt
twython_django.egg-info/requires.txt
twython_django.egg-info/top_level.txt
twython_django_oauth/__init__.py
twython_django_oauth/models.py
twython_django_oauth/urls.py
twython_django_oauth/views.py