Metadata-Version: 1.1
Name: twython-django
Version: 1.5.2
Summary: Django Integration for Twython -- the actively maintained, pure Python wrapper for the Twitter API. Supports both normal and streaming Twitter APIs
Home-page: https://github.com/ryanmcgrath/twython-django/tree/master
Author: Ryan McGrath
Author-email: ryan@venodesigns.net
License: The MIT License
